spiderpen/__init__.py
spiderpen-0.1.0.dist-info/LICENSE
spiderpen-0.1.0.dist-info/METADATA
spiderpen-0.1.0.dist-info/WHEEL
spiderpen-0.1.0.dist-info/top_level.txt
spiderpen-0.1.0.dist-info/RECORD
