Metadata-Version: 2.1
Name: spiderpen
Version: 0.1.0
Summary: Python library for controlling a plotter model complementary to the LEGO Boost 17101 set
Home-page: https://github.com/valentin-burillier/spiderpen
Author: Valentin Burillier
Author-email: burillier.v@gmail.com
License: UNKNOWN
Keywords: LEGO,ROBOTICS
Platform: UNKNOWN
Requires: pylgbst
License-File: LICENSE
